{
  "users": [
    {
      "username": "admin",
      "password": "aplan",
      "expiration_date": "2025-09-05"
    },
    {
      "username": "다린",
      "password": "신다린",
      "expiration_date": "2025-09-30"
    },
    {
      "username": "관리자",
      "password": "",
      "expiration_date": "2025-09-30"
    },
    {
      "username": "user4",
      "password": "aplan03",
      "expiration_date": "2025-09-30"
    },
    {
      "username": "user5",
      "password": "aplan04",
      "expiration_date": "2025-09-30"
    },
    {
      "username": "user6",
      "password": "aplan05",
      "expiration_date": "2025-09-30"
    },
    {
      "username": "user7",
      "password": "aplan06",
      "expiration_date": "2025-09-30"
    },
    {
      "username": "user8",
      "password": "aplan07",
      "expiration_date": "2025-09-30"
    },
    {
      "username": "user9",
      "password": "aplan08",
      "expiration_date": "2025-09-30"
    },
    {
      "username": "user10",
      "password": "aplan09",
      "expiration_date": "2025-09-30"
    }
  ]
}
